{
    "code": 200,
    "category": 4,
    "result": [
        {
            "id": 2062765721,
            "type": 1,
            "name": "嘉宾 | 曹导：我靠流量为生，我不是自由职业者",
            "copywriter": "编辑推荐：一起来聊聊网络人的何去何从",
            "picUrl": "http://p1.music.126.net/OV9VB96FPJkRsvC8a3hwFw==/109951164311305318.jpg",
            "canDislike": false,
            "program": {
                "mainSong": {
                    "name": "嘉宾 | 曹导：我靠流量为生，我不是自由职业者",
                    "id": 1385656357,
                    "position": 0,
                    "alias": [],
                    "status": 0,
                    "fee": 0,
                    "copyrightId": 0,
                    "disc": "",
                    "no": 0,
                    "artists": [
                        {
                            "name": "",
                            "id": 0,
                            "picId": 0,
                            "img1v1Id": 0,
                            "briefDesc": "",
                            "picUrl": "http://p2.music.126.net/6y-UleORITEDbvrOLV0Q8A==/5639395138885805.jpg",
                            "img1v1Url": "http://p2.music.126.net/6y-UleORITEDbvrOLV0Q8A==/5639395138885805.jpg",
                            "albumSize": 0,
                            "alias": [],
                            "trans": "",
                            "musicSize": 0,
                            "topicPerson": 0
                        }
                    ],
                    "album": {
                        "name": null,
                        "id": 0,
                        "type": null,
                        "size": 0,
                        "picId": 0,
                        "blurPicUrl": null,
                        "companyId": 0,
                        "pic": 0,
                        "picUrl": "http://p2.music.126.net/UeTuwE7pvjBpypWLudqukA==/3132508627578625.jpg",
                        "publishTime": 0,
                        "description": "",
                        "tags": "",
                        "company": null,
                        "briefDesc": "",
                        "artist": {
                            "name": "",
                            "id": 0,
                            "picId": 0,
                            "img1v1Id": 0,
                            "briefDesc": "",
                            "picUrl": "http://p2.music.126.net/6y-UleORITEDbvrOLV0Q8A==/5639395138885805.jpg",
                            "img1v1Url": "http://p2.music.126.net/6y-UleORITEDbvrOLV0Q8A==/5639395138885805.jpg",
                            "albumSize": 0,
                            "alias": [],
                            "trans": "",
                            "musicSize": 0,
                            "topicPerson": 0
                        },
                        "songs": [],
                        "alias": [],
                        "status": 0,
                        "copyrightId": 0,
                        "commentThreadId": "R_AL_3_0",
                        "artists": [
                            {
                                "name": "",
                                "id": 0,
                                "picId": 0,
                                "img1v1Id": 0,
                                "briefDesc": "",
                                "picUrl": "http://p2.music.126.net/6y-UleORITEDbvrOLV0Q8A==/5639395138885805.jpg",
                                "img1v1Url": "http://p2.music.126.net/6y-UleORITEDbvrOLV0Q8A==/5639395138885805.jpg",
                                "albumSize": 0,
                                "alias": [],
                                "trans": "",
                                "musicSize": 0,
                                "topicPerson": 0
                            }
                        ],
                        "subType": null,
                        "transName": null,
                        "mark": 0
                    },
                    "starred": false,
                    "popularity": 5,
                    "score": 5,
                    "starredNum": 0,
                    "duration": 2386224,
                    "playedNum": 0,
                    "dayPlays": 0,
                    "hearTime": 0,
                    "ringtone": null,
                    "crbt": null,
                    "audition": null,
                    "copyFrom": "",
                    "commentThreadId": "R_SO_4_1385656357",
                    "rtUrl": null,
                    "ftype": 0,
                    "rtUrls": [],
                    "copyright": 0,
                    "transName": null,
                    "sign": null,
                    "mark": 0,
                    "bMusic": {
                        "name": null,
                        "id": 3911772358,
                        "size": 57277956,
                        "extension": "mp3",
                        "sr": 48000,
                        "dfsId": 0,
                        "bitrate": 192000,
                        "playTime": 2386224,
                        "volumeDelta": 0
                    },
                    "mp3Url": null,
                    "rtype": 0,
                    "rurl": null,
                    "mvid": 0,
                    "hMusic": null,
                    "mMusic": {
                        "name": null,
                        "id": 3911772358,
                        "size": 57277956,
                        "extension": "mp3",
                        "sr": 48000,
                        "dfsId": 0,
                        "bitrate": 192000,
                        "playTime": 2386224,
                        "volumeDelta": 0
                    },
                    "lMusic": {
                        "name": null,
                        "id": 3911772358,
                        "size": 57277956,
                        "extension": "mp3",
                        "sr": 48000,
                        "dfsId": 0,
                        "bitrate": 192000,
                        "playTime": 2386224,
                        "volumeDelta": 0
                    }
                },
                "songs": null,
                "dj": {
                    "defaultAvatar": false,
                    "province": 1000000,
                    "authStatus": 0,
                    "followed": false,
                    "avatarUrl": "http://p1.music.126.net/PKB0nloMeR6U-E4top8SZg==/3276544659771024.jpg",
                    "accountStatus": 0,
                    "gender": 2,
                    "city": 1004400,
                    "birthday": 1445788800000,
                    "userId": 100679611,
                    "userType": 0,
                    "nickname": "The_F_Word",
                    "signature": "",
                    "description": "",
                    "detailDescription": "",
                    "avatarImgId": 3276544659771024,
                    "backgroundImgId": 1415071467076447,
                    "backgroundUrl": "http://p1.music.126.net/qCaHWNtzp1Y_CfywKctv1Q==/1415071467076447.jpg",
                    "authority": 0,
                    "mutual": false,
                    "expertTags": null,
                    "experts": null,
                    "djStatus": 10,
                    "vipType": 0,
                    "remarkName": null,
                    "backgroundImgIdStr": "1415071467076447",
                    "avatarImgIdStr": "3276544659771024",
                    "brand": "The F Word"
                },
                "blurCoverUrl": "http://music.163.com/api/dj/img/blur/109951164311305318",
                "radio": {
                    "id": 4894020,
                    "dj": null,
                    "name": "The F Word",
                    "picUrl": "http://p1.music.126.net/2_M3_c_4K4Ac-uKR-OXuLA==/1366692953713539.jpg",
                    "desc": "两个女生，一个话筒，每周探讨女权新鲜事。F is for feminism.\n搜索the-f-word和我们做更多互动。",
                    "subCount": 16559,
                    "programCount": 49,
                    "createTime": 1446413822344,
                    "categoryId": 5,
                    "category": "脱口秀",
                    "radioFeeType": 0,
                    "feeScope": 0,
                    "buyed": false,
                    "videos": null,
                    "finished": false,
                    "underShelf": false,
                    "purchaseCount": 0,
                    "price": 0,
                    "originalPrice": 0,
                    "discountPrice": null,
                    "lastProgramCreateTime": 1566382825540,
                    "lastProgramName": null,
                    "lastProgramId": 2062765721,
                    "picId": 1366692953713539,
                    "rcmdText": "每周探讨女权新鲜事",
                    "hightQuality": false,
                    "whiteList": false,
                    "composeVideo": false
                },
                "subscribedCount": 0,
                "reward": false,
                "mainTrackId": 1385656357,
                "serialNum": 49,
                "listenerCount": 6218,
                "name": "嘉宾 | 曹导：我靠流量为生，我不是自由职业者",
                "id": 2062765721,
                "createTime": 1566382825540,
                "description": "[头图来自曹导]\n\n曹导有80多万粉丝，80多期视频。她自称宇宙的孩子，靠流量为生，但不推荐他人盲目追求全职vlogger这个职业。在9102年，像曹导这样倚赖互联网上生存的年轻少男少女有千千万。我们和其中一位既特殊又普通的人聊了聊在网络的注视下生活有何风险，金钱与融资，还有网络人的何去何从。推荐大家在听本期播客之前，先搜索“曹导导”，看一两个视频，先了解一下本期嘉宾。\n\n两个女生，一个话筒，每月半小时探讨女权新鲜事。F is for feminism. 关注微信公号 the-f-word 回复节目序列号可以阅读节目对应图文推送。\n\n[本期提到]\n\nPapiTube （Papi酱旗下网络平台）\n千面娇娃杨老师\n本冰\n大概是井越\n你好_竹子\n我是何同学\n马鲨鲨\nCasey Neistat\n\n[背景音乐]\n\nLizzo - Truth Hurts\nDaniel Kaede - When the Ocean Sleeps - Epidemic Sounds\nThese Old Bones - Sunrise Stadium - Epidemic Sounds\nThe Fly Guy Five - Upbeat Flat Feet - Epidemic Sounds",
                "userId": 100679611,
                "coverUrl": "http://p1.music.126.net/OV9VB96FPJkRsvC8a3hwFw==/109951164311305318.jpg",
                "commentThreadId": "A_DJ_1_2062765721",
                "channels": [
                    "脱口秀"
                ],
                "titbits": null,
                "titbitImages": null,
                "pubStatus": 1,
                "trackCount": 1,
                "bdAuditStatus": 2,
                "programFeeType": 0,
                "buyed": false,
                "programDesc": null,
                "h5Links": [],
                "coverId": 109951164311305310,
                "adjustedPlayCount": 6218,
                "canReward": true,
                "auditStatus": 0,
                "publish": true,
                "duration": 2386224,
                "isPublish": true
            },
            "alg": "featured"
        },
        {
            "id": 2062785750,
            "type": 1,
            "name": "《芒种》抖音版",
            "copywriter": "编辑推荐：来听大热单曲《芒种》",
            "picUrl": "http://p1.music.126.net/SWVMm4ZJo26MtmZQ5iQEcg==/109951163928376797.jpg",
            "canDislike": false,
            "program": {
                "mainSong": {
                    "name": "《芒种》抖音版",
                    "id": 1385951867,
                    "position": 0,
                    "alias": [],
                    "status": 0,
                    "fee": 0,
                    "copyrightId": 0,
                    "disc": "",
                    "no": 0,
                    "artists": [
                        {
                            "name": "",
                            "id": 0,
                            "picId": 0,
                            "img1v1Id": 0,
                            "briefDesc": "",
                            "picUrl": "http://p2.music.126.net/6y-UleORITEDbvrOLV0Q8A==/5639395138885805.jpg",
                            "img1v1Url": "http://p2.music.126.net/6y-UleORITEDbvrOLV0Q8A==/5639395138885805.jpg",
                            "albumSize": 0,
                            "alias": [],
                            "trans": "",
                            "musicSize": 0,
                            "topicPerson": 0
                        }
                    ],
                    "album": {
                        "name": null,
                        "id": 0,
                        "type": null,
                        "size": 0,
                        "picId": 0,
                        "blurPicUrl": null,
                        "companyId": 0,
                        "pic": 0,
                        "picUrl": "http://p2.music.126.net/UeTuwE7pvjBpypWLudqukA==/3132508627578625.jpg",
                        "publishTime": 0,
                        "description": "",
                        "tags": "",
                        "company": null,
                        "briefDesc": "",
                        "artist": {
                            "name": "",
                            "id": 0,
                            "picId": 0,
                            "img1v1Id": 0,
                            "briefDesc": "",
                            "picUrl": "http://p2.music.126.net/6y-UleORITEDbvrOLV0Q8A==/5639395138885805.jpg",
                            "img1v1Url": "http://p2.music.126.net/6y-UleORITEDbvrOLV0Q8A==/5639395138885805.jpg",
                            "albumSize": 0,
                            "alias": [],
                            "trans": "",
                            "musicSize": 0,
                            "topicPerson": 0
                        },
                        "songs": [],
                        "alias": [],
                        "status": 0,
                        "copyrightId": 0,
                        "commentThreadId": "R_AL_3_0",
                        "artists": [
                            {
                                "name": "",
                                "id": 0,
                                "picId": 0,
                                "img1v1Id": 0,
                                "briefDesc": "",
                                "picUrl": "http://p2.music.126.net/6y-UleORITEDbvrOLV0Q8A==/5639395138885805.jpg",
                                "img1v1Url": "http://p2.music.126.net/6y-UleORITEDbvrOLV0Q8A==/5639395138885805.jpg",
                                "albumSize": 0,
                                "alias": [],
                                "trans": "",
                                "musicSize": 0,
                                "topicPerson": 0
                            }
                        ],
                        "subType": null,
                        "transName": null,
                        "mark": 0
                    },
                    "starred": false,
                    "popularity": 5,
                    "score": 5,
                    "starredNum": 0,
                    "duration": 26644,
                    "playedNum": 0,
                    "dayPlays": 0,
                    "hearTime": 0,
                    "ringtone": null,
                    "crbt": null,
                    "audition": null,
                    "copyFrom": "",
                    "commentThreadId": "R_SO_4_1385951867",
                    "rtUrl": null,
                    "ftype": 0,
                    "rtUrls": [],
                    "copyright": 0,
                    "transName": null,
                    "sign": null,
                    "mark": 0,
                    "bMusic": {
                        "name": null,
                        "id": 3913868869,
                        "size": 1069892,
                        "extension": "mp3",
                        "sr": 44100,
                        "dfsId": 0,
                        "bitrate": 320000,
                        "playTime": 26644,
                        "volumeDelta": 0
                    },
                    "mp3Url": null,
                    "rtype": 0,
                    "rurl": null,
                    "mvid": 0,
                    "hMusic": {
                        "name": null,
                        "id": 3913868869,
                        "size": 1069892,
                        "extension": "mp3",
                        "sr": 44100,
                        "dfsId": 0,
                        "bitrate": 320000,
                        "playTime": 26644,
                        "volumeDelta": 0
                    },
                    "mMusic": null,
                    "lMusic": {
                        "name": null,
                        "id": 3913868869,
                        "size": 1069892,
                        "extension": "mp3",
                        "sr": 44100,
                        "dfsId": 0,
                        "bitrate": 320000,
                        "playTime": 26644,
                        "volumeDelta": 0
                    }
                },
                "songs": null,
                "dj": {
                    "defaultAvatar": false,
                    "province": 310000,
                    "authStatus": 1,
                    "followed": false,
                    "avatarUrl": "http://p1.music.126.net/cCr0DS_d-eBuDjQ7CUnw1A==/109951163958424476.jpg",
                    "accountStatus": 0,
                    "gender": 2,
                    "city": 310101,
                    "birthday": -2209017600000,
                    "userId": 585533000,
                    "userType": 4,
                    "nickname": "鱼大仙儿儿",
                    "signature": "",
                    "description": "",
                    "detailDescription": "",
                    "avatarImgId": 109951163958424480,
                    "backgroundImgId": 109951162868126480,
                    "backgroundUrl": "http://p1.music.126.net/_f8R60U9mZ42sSNvdPn2sQ==/109951162868126486.jpg",
                    "authority": 0,
                    "mutual": false,
                    "expertTags": null,
                    "experts": {
                        "1": "音乐原创视频达人"
                    },
                    "djStatus": 10,
                    "vipType": 11,
                    "remarkName": null,
                    "backgroundImgIdStr": "109951162868126486",
                    "avatarImgIdStr": "109951163958424476",
                    "avatarImgId_str": "109951163958424476",
                    "brand": "鱼大仙儿"
                },
                "blurCoverUrl": "http://music.163.com/api/dj/img/blur/109951163928376797",
                "radio": {
                    "id": 792958387,
                    "dj": null,
                    "name": "鱼大仙儿",
                    "picUrl": "http://p1.music.126.net/SWVMm4ZJo26MtmZQ5iQEcg==/109951163928376797.jpg",
                    "desc": "这里会发布各个短视频里的歌曲\n欢迎订阅！",
                    "subCount": 50491,
                    "programCount": 52,
                    "createTime": 1552670316888,
                    "categoryId": 2001,
                    "category": "创作|翻唱",
                    "radioFeeType": 0,
                    "feeScope": 0,
                    "buyed": false,
                    "videos": null,
                    "finished": false,
                    "underShelf": false,
                    "purchaseCount": 0,
                    "price": 0,
                    "originalPrice": 0,
                    "discountPrice": null,
                    "lastProgramCreateTime": 1566492623885,
                    "lastProgramName": null,
                    "lastProgramId": 2062785750,
                    "picId": 109951163928376800,
                    "rcmdText": null,
                    "hightQuality": false,
                    "whiteList": false,
                    "composeVideo": false
                },
                "subscribedCount": 1,
                "reward": false,
                "mainTrackId": 1385951867,
                "serialNum": 52,
                "listenerCount": 33963,
                "name": "《芒种》抖音版",
                "id": 2062785750,
                "createTime": 1566492623885,
                "description": "《芒种》抖音版",
                "userId": 585533000,
                "coverUrl": "http://p1.music.126.net/SWVMm4ZJo26MtmZQ5iQEcg==/109951163928376797.jpg",
                "commentThreadId": "A_DJ_1_2062785750",
                "channels": [],
                "titbits": null,
                "titbitImages": null,
                "pubStatus": 1,
                "trackCount": 1,
                "bdAuditStatus": 2,
                "programFeeType": 0,
                "buyed": false,
                "programDesc": null,
                "h5Links": [],
                "coverId": 109951163928376800,
                "adjustedPlayCount": 33963,
                "canReward": false,
                "auditStatus": 0,
                "publish": true,
                "duration": 26644,
                "isPublish": true
            },
            "alg": "featured"
        },
        {
            "id": 2062133049,
            "type": 1,
            "name": "Señorita / 20秒",
            "copywriter": "热门电台节目推荐",
            "picUrl": "http://p1.music.126.net/2q7Xq5ohhEqynZJfh10JPQ==/1909851697595961.jpg",
            "canDislike": true,
            "program": {
                "mainSong": {
                    "name": "Señorita / 20秒",
                    "id": 1378012246,
                    "position": 0,
                    "alias": [],
                    "status": 0,
                    "fee": 0,
                    "copyrightId": 0,
                    "disc": "",
                    "no": 0,
                    "artists": [
                        {
                            "name": "",
                            "id": 0,
                            "picId": 0,
                            "img1v1Id": 0,
                            "briefDesc": "",
                            "picUrl": "http://p2.music.126.net/6y-UleORITEDbvrOLV0Q8A==/5639395138885805.jpg",
                            "img1v1Url": "http://p2.music.126.net/6y-UleORITEDbvrOLV0Q8A==/5639395138885805.jpg",
                            "albumSize": 0,
                            "alias": [],
                            "trans": "",
                            "musicSize": 0,
                            "topicPerson": 0
                        }
                    ],
                    "album": {
                        "name": null,
                        "id": 0,
                        "type": null,
                        "size": 0,
                        "picId": 0,
                        "blurPicUrl": null,
                        "companyId": 0,
                        "pic": 0,
                        "picUrl": "http://p2.music.126.net/UeTuwE7pvjBpypWLudqukA==/3132508627578625.jpg",
                        "publishTime": 0,
                        "description": "",
                        "tags": "",
                        "company": null,
                        "briefDesc": "",
                        "artist": {
                            "name": "",
                            "id": 0,
                            "picId": 0,
                            "img1v1Id": 0,
                            "briefDesc": "",
                            "picUrl": "http://p2.music.126.net/6y-UleORITEDbvrOLV0Q8A==/5639395138885805.jpg",
                            "img1v1Url": "http://p2.music.126.net/6y-UleORITEDbvrOLV0Q8A==/5639395138885805.jpg",
                            "albumSize": 0,
                            "alias": [],
                            "trans": "",
                            "musicSize": 0,
                            "topicPerson": 0
                        },
                        "songs": [],
                        "alias": [],
                        "status": 0,
                        "copyrightId": 0,
                        "commentThreadId": "R_AL_3_0",
                        "artists": [
                            {
                                "name": "",
                                "id": 0,
                                "picId": 0,
                                "img1v1Id": 0,
                                "briefDesc": "",
                                "picUrl": "http://p2.music.126.net/6y-UleORITEDbvrOLV0Q8A==/5639395138885805.jpg",
                                "img1v1Url": "http://p2.music.126.net/6y-UleORITEDbvrOLV0Q8A==/5639395138885805.jpg",
                                "albumSize": 0,
                                "alias": [],
                                "trans": "",
                                "musicSize": 0,
                                "topicPerson": 0
                            }
                        ],
                        "subType": null,
                        "transName": null,
                        "mark": 0
                    },
                    "starred": false,
                    "popularity": 60,
                    "score": 60,
                    "starredNum": 0,
                    "duration": 20610,
                    "playedNum": 0,
                    "dayPlays": 0,
                    "hearTime": 0,
                    "ringtone": null,
                    "crbt": null,
                    "audition": null,
                    "copyFrom": "",
                    "commentThreadId": "R_SO_4_1378012246",
                    "rtUrl": null,
                    "ftype": 0,
                    "rtUrls": [],
                    "copyright": 0,
                    "transName": null,
                    "sign": null,
                    "mark": 0,
                    "bMusic": {
                        "name": null,
                        "id": 3853241255,
                        "size": 824424,
                        "extension": "mp3",
                        "sr": 44100,
                        "dfsId": 0,
                        "bitrate": 320000,
                        "playTime": 20610,
                        "volumeDelta": 0
                    },
                    "mp3Url": null,
                    "rtype": 0,
                    "rurl": null,
                    "mvid": 0,
                    "hMusic": {
                        "name": null,
                        "id": 3853241255,
                        "size": 824424,
                        "extension": "mp3",
                        "sr": 44100,
                        "dfsId": 0,
                        "bitrate": 320000,
                        "playTime": 20610,
                        "volumeDelta": 0
                    },
                    "mMusic": null,
                    "lMusic": {
                        "name": null,
                        "id": 3853241255,
                        "size": 824424,
                        "extension": "mp3",
                        "sr": 44100,
                        "dfsId": 0,
                        "bitrate": 320000,
                        "playTime": 20610,
                        "volumeDelta": 0
                    }
                },
                "songs": null,
                "dj": {
                    "defaultAvatar": false,
                    "province": 1000000,
                    "authStatus": 0,
                    "followed": false,
                    "avatarUrl": "http://p1.music.126.net/MdFvhw9aVU6CRGxN_m_pDA==/109951163866984763.jpg",
                    "accountStatus": 0,
                    "gender": 2,
                    "city": 1010000,
                    "birthday": 980343733967,
                    "userId": 104853640,
                    "userType": 0,
                    "nickname": "xswagger",
                    "signature": "是SWAGGER啦！~",
                    "description": "",
                    "detailDescription": "",
                    "avatarImgId": 109951163866984770,
                    "backgroundImgId": 109951164074383250,
                    "backgroundUrl": "http://p1.music.126.net/nA-IQ9KXU7r0hDWiA5Q7_Q==/109951164074383253.jpg",
                    "authority": 0,
                    "mutual": false,
                    "expertTags": null,
                    "experts": null,
                    "djStatus": 10,
                    "vipType": 0,
                    "remarkName": null,
                    "backgroundImgIdStr": "109951164074383253",
                    "avatarImgIdStr": "109951163866984763",
                    "avatarImgId_str": "109951163866984763",
                    "brand": "#SWAGGER"
                },
                "blurCoverUrl": "http://music.163.com/api/dj/img/blur/1909851697595961",
                "radio": {
                    "id": 347370082,
                    "dj": null,
                    "name": "#SWAGGER",
                    "picUrl": "http://p1.music.126.net/iX0b0xLiPDkh9sR9XbCTXw==/1282030558050069.jpg",
                    "desc": "一起听歌吧✨🐰",
                    "subCount": 23358,
                    "programCount": 10,
                    "createTime": 1485436439779,
                    "categoryId": 2001,
                    "category": "创作|翻唱",
                    "radioFeeType": 0,
                    "feeScope": 0,
                    "buyed": false,
                    "videos": null,
                    "finished": false,
                    "underShelf": false,
                    "purchaseCount": 0,
                    "price": 0,
                    "originalPrice": 0,
                    "discountPrice": null,
                    "lastProgramCreateTime": 1566573442662,
                    "lastProgramName": null,
                    "lastProgramId": 2062820222,
                    "picId": 1282030558050069,
                    "rcmdText": null,
                    "hightQuality": false,
                    "whiteList": false,
                    "composeVideo": false
                },
                "subscribedCount": 0,
                "reward": false,
                "mainTrackId": 1378012246,
                "serialNum": 7,
                "listenerCount": 3439854,
                "name": "Señorita / 20秒",
                "id": 2062133049,
                "createTime": 1563152942479,
                "description": "I love it when you call me Señorita，\nI wish I could pretend I didn't need ya，\nBut every touch is ooh la la la，\nIt's true la la la，Ooh I should be runnin'，\nOoh you keep me coming for ya",
                "userId": 104853640,
                "coverUrl": "http://p1.music.126.net/2q7Xq5ohhEqynZJfh10JPQ==/1909851697595961.jpg",
                "commentThreadId": "A_DJ_1_2062133049",
                "channels": [],
                "titbits": null,
                "titbitImages": null,
                "pubStatus": 1,
                "trackCount": 0,
                "bdAuditStatus": 2,
                "programFeeType": 0,
                "buyed": false,
                "programDesc": null,
                "h5Links": [],
                "coverId": 1909851697595961,
                "adjustedPlayCount": 3439854,
                "canReward": false,
                "auditStatus": 0,
                "publish": true,
                "duration": 20610,
                "isPublish": true
            },
            "alg": "hot_server"
        },
        {
            "id": 2062759594,
            "type": 1,
            "name": "TI9 Intro Music",
            "copywriter": "热门电台节目推荐",
            "picUrl": "http://p1.music.126.net/nDHrBY2dC-k9qOrnUQxk_Q==/109951164310419966.jpg",
            "canDislike": true,
            "program": {
                "mainSong": {
                    "name": "TI9 Intro Music",
                    "id": 1385589270,
                    "position": 0,
                    "alias": [],
                    "status": 0,
                    "fee": 0,
                    "copyrightId": 0,
                    "disc": "",
                    "no": 0,
                    "artists": [
                        {
                            "name": "",
                            "id": 0,
                            "picId": 0,
                            "img1v1Id": 0,
                            "briefDesc": "",
                            "picUrl": "http://p2.music.126.net/6y-UleORITEDbvrOLV0Q8A==/5639395138885805.jpg",
                            "img1v1Url": "http://p2.music.126.net/6y-UleORITEDbvrOLV0Q8A==/5639395138885805.jpg",
                            "albumSize": 0,
                            "alias": [],
                            "trans": "",
                            "musicSize": 0,
                            "topicPerson": 0
                        }
                    ],
                    "album": {
                        "name": null,
                        "id": 0,
                        "type": null,
                        "size": 0,
                        "picId": 0,
                        "blurPicUrl": null,
                        "companyId": 0,
                        "pic": 0,
                        "picUrl": "http://p2.music.126.net/UeTuwE7pvjBpypWLudqukA==/3132508627578625.jpg",
                        "publishTime": 0,
                        "description": "",
                        "tags": "",
                        "company": null,
                        "briefDesc": "",
                        "artist": {
                            "name": "",
                            "id": 0,
                            "picId": 0,
                            "img1v1Id": 0,
                            "briefDesc": "",
                            "picUrl": "http://p2.music.126.net/6y-UleORITEDbvrOLV0Q8A==/5639395138885805.jpg",
                            "img1v1Url": "http://p2.music.126.net/6y-UleORITEDbvrOLV0Q8A==/5639395138885805.jpg",
                            "albumSize": 0,
                            "alias": [],
                            "trans": "",
                            "musicSize": 0,
                            "topicPerson": 0
                        },
                        "songs": [],
                        "alias": [],
                        "status": 0,
                        "copyrightId": 0,
                        "commentThreadId": "R_AL_3_0",
                        "artists": [
                            {
                                "name": "",
                                "id": 0,
                                "picId": 0,
                                "img1v1Id": 0,
                                "briefDesc": "",
                                "picUrl": "http://p2.music.126.net/6y-UleORITEDbvrOLV0Q8A==/5639395138885805.jpg",
                                "img1v1Url": "http://p2.music.126.net/6y-UleORITEDbvrOLV0Q8A==/5639395138885805.jpg",
                                "albumSize": 0,
                                "alias": [],
                                "trans": "",
                                "musicSize": 0,
                                "topicPerson": 0
                            }
                        ],
                        "subType": null,
                        "transName": null,
                        "mark": 0
                    },
                    "starred": false,
                    "popularity": 25,
                    "score": 25,
                    "starredNum": 0,
                    "duration": 96951,
                    "playedNum": 0,
                    "dayPlays": 0,
                    "hearTime": 0,
                    "ringtone": null,
                    "crbt": null,
                    "audition": null,
                    "copyFrom": "",
                    "commentThreadId": "R_SO_4_1385589270",
                    "rtUrl": null,
                    "ftype": 0,
                    "rtUrls": [],
                    "copyright": 0,
                    "transName": null,
                    "sign": null,
                    "mark": 0,
                    "bMusic": {
                        "name": null,
                        "id": 3911260273,
                        "size": 11313677,
                        "extension": "mp3",
                        "sr": 48000,
                        "dfsId": 0,
                        "bitrate": 933000,
                        "playTime": 96951,
                        "volumeDelta": 0
                    },
                    "mp3Url": null,
                    "rtype": 0,
                    "rurl": null,
                    "mvid": 0,
                    "hMusic": {
                        "name": null,
                        "id": 3911260273,
                        "size": 11313677,
                        "extension": "mp3",
                        "sr": 48000,
                        "dfsId": 0,
                        "bitrate": 933000,
                        "playTime": 96951,
                        "volumeDelta": 0
                    },
                    "mMusic": null,
                    "lMusic": {
                        "name": null,
                        "id": 3911260273,
                        "size": 11313677,
                        "extension": "mp3",
                        "sr": 48000,
                        "dfsId": 0,
                        "bitrate": 933000,
                        "playTime": 96951,
                        "volumeDelta": 0
                    }
                },
                "songs": null,
                "dj": {
                    "defaultAvatar": false,
                    "province": 330000,
                    "authStatus": 0,
                    "followed": false,
                    "avatarUrl": "http://p1.music.126.net/5eH62u3wVQ0_KVOM0NX0UQ==/109951162971835343.jpg",
                    "accountStatus": 0,
                    "gender": 1,
                    "city": 330300,
                    "birthday": 631123200000,
                    "userId": 106914747,
                    "userType": 0,
                    "nickname": "HAHAWTF",
                    "signature": "",
                    "description": "",
                    "detailDescription": "",
                    "avatarImgId": 109951162971835340,
                    "backgroundImgId": 109951163277015600,
                    "backgroundUrl": "http://p1.music.126.net/ij2zqVXtUZvqWFWsgtonKA==/109951163277015595.jpg",
                    "authority": 0,
                    "mutual": false,
                    "expertTags": null,
                    "experts": null,
                    "djStatus": 10,
                    "vipType": 0,
                    "remarkName": null,
                    "backgroundImgIdStr": "109951163277015595",
                    "avatarImgIdStr": "109951162971835343",
                    "avatarImgId_str": "109951162971835343",
                    "brand": "DOTA2音乐包合集"
                },
                "blurCoverUrl": "http://music.163.com/api/dj/img/blur/109951164310419966",
                "radio": {
                    "id": 332447061,
                    "dj": null,
                    "name": "DOTA2音乐包合集",
                    "picUrl": "http://p1.music.126.net/MdPj3m8Z8YQqIkjoKa-Uyg==/1404076351898468.jpg",
                    "desc": "感谢订阅\n★ 更新了TI9音乐包\n电台内所有音乐为搬运作品，仅用于个人收听，请勿作商业用途。\n动态里附有源文件下载链接\nlaning: 对线音乐\ncountdown : 开局准备音乐\nui_hero_select: 选人界面音乐\nroshan: 打肉山音乐\nui_main: 主菜单寻找比赛音乐\nui_startup: 主菜单音乐\nkilled: 死亡音乐\nbattle:战斗音乐\nsmoke:开雾音乐",
                    "subCount": 21883,
                    "programCount": 391,
                    "createTime": 1458364814864,
                    "categoryId": 10002,
                    "category": "3D|电子",
                    "radioFeeType": 0,
                    "feeScope": 0,
                    "buyed": false,
                    "videos": null,
                    "finished": false,
                    "underShelf": false,
                    "purchaseCount": 0,
                    "price": 0,
                    "originalPrice": 0,
                    "discountPrice": null,
                    "lastProgramCreateTime": 1566358171090,
                    "lastProgramName": null,
                    "lastProgramId": 2062759594,
                    "picId": 1404076351898468,
                    "rcmdText": null,
                    "hightQuality": false,
                    "whiteList": false,
                    "composeVideo": false
                },
                "subscribedCount": 0,
                "reward": false,
                "mainTrackId": 1385589270,
                "serialNum": 391,
                "listenerCount": 246652,
                "name": "TI9 Intro Music",
                "id": 2062759594,
                "createTime": 1566358171090,
                "description": "TI9比赛选手介绍音乐\n作曲家：Sandman Theory\n原曲链接：\nhttps://soundcloud.com/sandmantheory/dota-2-ti9-player-walk-in\n\nhttps://soundcloud.com/sandmantheory/dota-2-ti9-player-walk-in-alt\n此曲为合并版",
                "userId": 106914747,
                "coverUrl": "http://p1.music.126.net/nDHrBY2dC-k9qOrnUQxk_Q==/109951164310419966.jpg",
                "commentThreadId": "A_DJ_1_2062759594",
                "channels": [],
                "titbits": null,
                "titbitImages": null,
                "pubStatus": 1,
                "trackCount": 0,
                "bdAuditStatus": 2,
                "programFeeType": 0,
                "buyed": false,
                "programDesc": null,
                "h5Links": [],
                "coverId": 109951164310419970,
                "adjustedPlayCount": 246652,
                "canReward": false,
                "auditStatus": 0,
                "publish": true,
                "duration": 96951,
                "isPublish": true
            },
            "alg": "hot_server"
        },
        {
            "id": 2062500755,
            "type": 1,
            "name": "飞行日记",
            "copywriter": "热门电台节目推荐",
            "picUrl": "http://p1.music.126.net/pjOloya3pAZcAYS5a2Fsow==/109951163810252191.jpg",
            "canDislike": true,
            "program": {
                "mainSong": {
                    "name": "飞行日记",
                    "id": 1382305872,
                    "position": 0,
                    "alias": [],
                    "status": 0,
                    "fee": 0,
                    "copyrightId": 0,
                    "disc": "",
                    "no": 0,
                    "artists": [
                        {
                            "name": "",
                            "id": 0,
                            "picId": 0,
                            "img1v1Id": 0,
                            "briefDesc": "",
                            "picUrl": "http://p2.music.126.net/6y-UleORITEDbvrOLV0Q8A==/5639395138885805.jpg",
                            "img1v1Url": "http://p2.music.126.net/6y-UleORITEDbvrOLV0Q8A==/5639395138885805.jpg",
                            "albumSize": 0,
                            "alias": [],
                            "trans": "",
                            "musicSize": 0,
                            "topicPerson": 0
                        }
                    ],
                    "album": {
                        "name": null,
                        "id": 0,
                        "type": null,
                        "size": 0,
                        "picId": 0,
                        "blurPicUrl": null,
                        "companyId": 0,
                        "pic": 0,
                        "picUrl": "http://p2.music.126.net/UeTuwE7pvjBpypWLudqukA==/3132508627578625.jpg",
                        "publishTime": 0,
                        "description": "",
                        "tags": "",
                        "company": null,
                        "briefDesc": "",
                        "artist": {
                            "name": "",
                            "id": 0,
                            "picId": 0,
                            "img1v1Id": 0,
                            "briefDesc": "",
                            "picUrl": "http://p2.music.126.net/6y-UleORITEDbvrOLV0Q8A==/5639395138885805.jpg",
                            "img1v1Url": "http://p2.music.126.net/6y-UleORITEDbvrOLV0Q8A==/5639395138885805.jpg",
                            "albumSize": 0,
                            "alias": [],
                            "trans": "",
                            "musicSize": 0,
                            "topicPerson": 0
                        },
                        "songs": [],
                        "alias": [],
                        "status": 0,
                        "copyrightId": 0,
                        "commentThreadId": "R_AL_3_0",
                        "artists": [
                            {
                                "name": "",
                                "id": 0,
                                "picId": 0,
                                "img1v1Id": 0,
                                "briefDesc": "",
                                "picUrl": "http://p2.music.126.net/6y-UleORITEDbvrOLV0Q8A==/5639395138885805.jpg",
                                "img1v1Url": "http://p2.music.126.net/6y-UleORITEDbvrOLV0Q8A==/5639395138885805.jpg",
                                "albumSize": 0,
                                "alias": [],
                                "trans": "",
                                "musicSize": 0,
                                "topicPerson": 0
                            }
                        ],
                        "subType": null,
                        "transName": null,
                        "mark": 0
                    },
                    "starred": false,
                    "popularity": 25,
                    "score": 25,
                    "starredNum": 0,
                    "duration": 26070,
                    "playedNum": 0,
                    "dayPlays": 0,
                    "hearTime": 0,
                    "ringtone": null,
                    "crbt": null,
                    "audition": null,
                    "copyFrom": "",
                    "commentThreadId": "R_SO_4_1382305872",
                    "rtUrl": null,
                    "ftype": 0,
                    "rtUrls": [],
                    "copyright": 0,
                    "transName": null,
                    "sign": null,
                    "mark": 0,
                    "bMusic": {
                        "name": null,
                        "id": 3885905872,
                        "size": 1042808,
                        "extension": "mp3",
                        "sr": 44100,
                        "dfsId": 0,
                        "bitrate": 320000,
                        "playTime": 26070,
                        "volumeDelta": 0
                    },
                    "mp3Url": null,
                    "rtype": 0,
                    "rurl": null,
                    "mvid": 0,
                    "hMusic": {
                        "name": null,
                        "id": 3885905872,
                        "size": 1042808,
                        "extension": "mp3",
                        "sr": 44100,
                        "dfsId": 0,
                        "bitrate": 320000,
                        "playTime": 26070,
                        "volumeDelta": 0
                    },
                    "mMusic": null,
                    "lMusic": {
                        "name": null,
                        "id": 3885905872,
                        "size": 1042808,
                        "extension": "mp3",
                        "sr": 44100,
                        "dfsId": 0,
                        "bitrate": 320000,
                        "playTime": 26070,
                        "volumeDelta": 0
                    }
                },
                "songs": null,
                "dj": {
                    "defaultAvatar": false,
                    "province": 310000,
                    "authStatus": 0,
                    "followed": false,
                    "avatarUrl": "http://p1.music.126.net/mxfbewC6yrygzUwNPetUiw==/109951164269895922.jpg",
                    "accountStatus": 0,
                    "gender": 2,
                    "city": 310101,
                    "birthday": 774028800000,
                    "userId": 60972460,
                    "userType": 0,
                    "nickname": "你的星冰乐",
                    "signature": "我想着伶俜一人独活",
                    "description": "",
                    "detailDescription": "",
                    "avatarImgId": 109951164269895920,
                    "backgroundImgId": 109951163689791310,
                    "backgroundUrl": "http://p1.music.126.net/0dccyur1oEwfxntFFPboFg==/109951163689791312.jpg",
                    "authority": 0,
                    "mutual": false,
                    "expertTags": null,
                    "experts": null,
                    "djStatus": 10,
                    "vipType": 11,
                    "remarkName": null,
                    "backgroundImgIdStr": "109951163689791312",
                    "avatarImgIdStr": "109951164269895922",
                    "avatarImgId_str": "109951164269895922",
                    "brand": "你的星冰乐"
                },
                "blurCoverUrl": "http://music.163.com/api/dj/img/blur/109951163810252191",
                "radio": {
                    "id": 792659457,
                    "dj": null,
                    "name": "你的星冰乐",
                    "picUrl": "http://p1.music.126.net/pjOloya3pAZcAYS5a2Fsow==/109951163810252191.jpg",
                    "desc": "不如陪我虚度时光",
                    "subCount": 16604,
                    "programCount": 17,
                    "createTime": 1548151004509,
                    "categoryId": 2001,
                    "category": "创作|翻唱",
                    "radioFeeType": 0,
                    "feeScope": 0,
                    "buyed": false,
                    "videos": null,
                    "finished": false,
                    "underShelf": false,
                    "purchaseCount": 0,
                    "price": 0,
                    "originalPrice": 0,
                    "discountPrice": null,
                    "lastProgramCreateTime": 1565526217287,
                    "lastProgramName": null,
                    "lastProgramId": 2062601444,
                    "picId": 109951163810252200,
                    "rcmdText": null,
                    "hightQuality": false,
                    "whiteList": false,
                    "composeVideo": false
                },
                "subscribedCount": 0,
                "reward": false,
                "mainTrackId": 1382305872,
                "serialNum": 16,
                "listenerCount": 1724713,
                "name": "飞行日记",
                "id": 2062500755,
                "createTime": 1564970988856,
                "description": "飞行日记",
                "userId": 60972460,
                "coverUrl": "http://p1.music.126.net/pjOloya3pAZcAYS5a2Fsow==/109951163810252191.jpg",
                "commentThreadId": "A_DJ_1_2062500755",
                "channels": [],
                "titbits": null,
                "titbitImages": null,
                "pubStatus": 1,
                "trackCount": 0,
                "bdAuditStatus": 2,
                "programFeeType": 0,
                "buyed": false,
                "programDesc": null,
                "h5Links": [],
                "coverId": 109951163810252200,
                "adjustedPlayCount": 1724713,
                "canReward": false,
                "auditStatus": 0,
                "publish": true,
                "duration": 26070,
                "isPublish": true
            },
            "alg": "hot_server"
        },
        {
            "id": 2062632294,
            "type": 1,
            "name": "忽而今夏（四合院版本）",
            "copywriter": "热门电台节目推荐",
            "picUrl": "http://p1.music.126.net/Dk8SWIUBmiiutKNK3rXRYw==/109951163773467863.jpg",
            "canDislike": true,
            "program": {
                "mainSong": {
                    "name": "忽而今夏（四合院版本）",
                    "id": 1383845262,
                    "position": 0,
                    "alias": [],
                    "status": 0,
                    "fee": 0,
                    "copyrightId": 0,
                    "disc": "",
                    "no": 0,
                    "artists": [
                        {
                            "name": "",
                            "id": 0,
                            "picId": 0,
                            "img1v1Id": 0,
                            "briefDesc": "",
                            "picUrl": "http://p2.music.126.net/6y-UleORITEDbvrOLV0Q8A==/5639395138885805.jpg",
                            "img1v1Url": "http://p2.music.126.net/6y-UleORITEDbvrOLV0Q8A==/5639395138885805.jpg",
                            "albumSize": 0,
                            "alias": [],
                            "trans": "",
                            "musicSize": 0,
                            "topicPerson": 0
                        }
                    ],
                    "album": {
                        "name": null,
                        "id": 0,
                        "type": null,
                        "size": 0,
                        "picId": 0,
                        "blurPicUrl": null,
                        "companyId": 0,
                        "pic": 0,
                        "picUrl": "http://p2.music.126.net/UeTuwE7pvjBpypWLudqukA==/3132508627578625.jpg",
                        "publishTime": 0,
                        "description": "",
                        "tags": "",
                        "company": null,
                        "briefDesc": "",
                        "artist": {
                            "name": "",
                            "id": 0,
                            "picId": 0,
                            "img1v1Id": 0,
                            "briefDesc": "",
                            "picUrl": "http://p2.music.126.net/6y-UleORITEDbvrOLV0Q8A==/5639395138885805.jpg",
                            "img1v1Url": "http://p2.music.126.net/6y-UleORITEDbvrOLV0Q8A==/5639395138885805.jpg",
                            "albumSize": 0,
                            "alias": [],
                            "trans": "",
                            "musicSize": 0,
                            "topicPerson": 0
                        },
                        "songs": [],
                        "alias": [],
                        "status": 0,
                        "copyrightId": 0,
                        "commentThreadId": "R_AL_3_0",
                        "artists": [
                            {
                                "name": "",
                                "id": 0,
                                "picId": 0,
                                "img1v1Id": 0,
                                "briefDesc": "",
                                "picUrl": "http://p2.music.126.net/6y-UleORITEDbvrOLV0Q8A==/5639395138885805.jpg",
                                "img1v1Url": "http://p2.music.126.net/6y-UleORITEDbvrOLV0Q8A==/5639395138885805.jpg",
                                "albumSize": 0,
                                "alias": [],
                                "trans": "",
                                "musicSize": 0,
                                "topicPerson": 0
                            }
                        ],
                        "subType": null,
                        "transName": null,
                        "mark": 0
                    },
                    "starred": false,
                    "popularity": 45,
                    "score": 45,
                    "starredNum": 0,
                    "duration": 17136,
                    "playedNum": 0,
                    "dayPlays": 0,
                    "hearTime": 0,
                    "ringtone": null,
                    "crbt": null,
                    "audition": null,
                    "copyFrom": "",
                    "commentThreadId": "R_SO_4_1383845262",
                    "rtUrl": null,
                    "ftype": 0,
                    "rtUrls": [],
                    "copyright": 0,
                    "transName": null,
                    "sign": null,
                    "mark": 0,
                    "bMusic": {
                        "name": null,
                        "id": 3896838264,
                        "size": 686631,
                        "extension": "mp3",
                        "sr": 44100,
                        "dfsId": 0,
                        "bitrate": 320000,
                        "playTime": 17136,
                        "volumeDelta": 0
                    },
                    "mp3Url": null,
                    "rtype": 0,
                    "rurl": null,
                    "mvid": 0,
                    "hMusic": {
                        "name": null,
                        "id": 3896838264,
                        "size": 686631,
                        "extension": "mp3",
                        "sr": 44100,
                        "dfsId": 0,
                        "bitrate": 320000,
                        "playTime": 17136,
                        "volumeDelta": 0
                    },
                    "mMusic": null,
                    "lMusic": {
                        "name": null,
                        "id": 3896838264,
                        "size": 686631,
                        "extension": "mp3",
                        "sr": 44100,
                        "dfsId": 0,
                        "bitrate": 320000,
                        "playTime": 17136,
                        "volumeDelta": 0
                    }
                },
                "songs": null,
                "dj": {
                    "defaultAvatar": false,
                    "province": 500000,
                    "authStatus": 1,
                    "followed": false,
                    "avatarUrl": "http://p1.music.126.net/r8nIfRBZS_xk0bX8kpLyFw==/109951164017499846.jpg",
                    "accountStatus": 0,
                    "gender": 1,
                    "city": 500101,
                    "birthday": 813168000000,
                    "userId": 426366432,
                    "userType": 4,
                    "nickname": "四十只烤翅",
                    "signature": "",
                    "description": "",
                    "detailDescription": "",
                    "avatarImgId": 109951164017499840,
                    "backgroundImgId": 109951164017495460,
                    "backgroundUrl": "http://p1.music.126.net/hWzTM8MCymkmyIFVWWKjbQ==/109951164017495459.jpg",
                    "authority": 0,
                    "mutual": false,
                    "expertTags": null,
                    "experts": null,
                    "djStatus": 10,
                    "vipType": 11,
                    "remarkName": null,
                    "backgroundImgIdStr": "109951164017495459",
                    "avatarImgIdStr": "109951164017499846",
                    "avatarImgId_str": "109951164017499846",
                    "brand": "四只烤翅"
                },
                "blurCoverUrl": "http://music.163.com/api/dj/img/blur/109951163773467863",
                "radio": {
                    "id": 792544462,
                    "dj": null,
                    "name": "四只烤翅",
                    "picUrl": "http://p1.music.126.net/Dk8SWIUBmiiutKNK3rXRYw==/109951163773467863.jpg",
                    "desc": "四只烤翅",
                    "subCount": 114798,
                    "programCount": 25,
                    "createTime": 1546664883212,
                    "categoryId": 2,
                    "category": "音乐故事",
                    "radioFeeType": 0,
                    "feeScope": 0,
                    "buyed": false,
                    "videos": null,
                    "finished": false,
                    "underShelf": false,
                    "purchaseCount": 0,
                    "price": 0,
                    "originalPrice": 0,
                    "discountPrice": null,
                    "lastProgramCreateTime": 1566606335256,
                    "lastProgramName": null,
                    "lastProgramId": 2062831263,
                    "picId": 109951163773467860,
                    "rcmdText": "",
                    "hightQuality": false,
                    "whiteList": false,
                    "composeVideo": false
                },
                "subscribedCount": 0,
                "reward": false,
                "mainTrackId": 1383845262,
                "serialNum": 24,
                "listenerCount": 2052386,
                "name": "忽而今夏（四合院版本）",
                "id": 2062632294,
                "createTime": 1565648798342,
                "description": "可是你还记得吗 那年盛夏\n那个傻瓜 说的傻话\n陪着你回家 陪着你长大\n每天要记得打电话\n可是你还记得吗...",
                "userId": 426366432,
                "coverUrl": "http://p1.music.126.net/Dk8SWIUBmiiutKNK3rXRYw==/109951163773467863.jpg",
                "commentThreadId": "A_DJ_1_2062632294",
                "channels": [
                    "音乐故事"
                ],
                "titbits": null,
                "titbitImages": null,
                "pubStatus": 1,
                "trackCount": 0,
                "bdAuditStatus": 2,
                "programFeeType": 0,
                "buyed": false,
                "programDesc": null,
                "h5Links": [],
                "coverId": 109951163773467860,
                "adjustedPlayCount": 2052386,
                "canReward": true,
                "auditStatus": 0,
                "publish": true,
                "duration": 17136,
                "isPublish": true
            },
            "alg": "hot_server"
        }
    ]
}